{"raw.rtx_kg2.nodes": {"rows": 500, "columns": 3, "file_size": 20803}, "int.embeddings": {"rows": 500, "columns": 2, "file_size": 7591}, "feat.rtx_kg2": {"rows": 500, "columns": 7, "file_size": 18418}, "raw.ground_truth.tp": {"rows": 50, "columns": 2, "file_size": 900}, "raw.ground_truth.tn": {"rows": 50, "columns": 2, "file_size": 887}, "prm.known_pairs": {"rows": 100, "columns": 5, "file_size": 6729}, "model_input.splits": {"rows": 100, "columns": 7, "file_size": 7963}, "model_input.enriched_splits": {"rows": 150, "columns": 7, "file_size": 8904}, "model_input.transformed_splits": {"rows": 150, "columns": 25}}